HISTORIE.TXT
HISTORY.TXT
MANIFEST.in
README.txt
ez_setup.py
setup.py
scripts/fancyhash.py
scripts/py-env.py
scripts/rexxbi_demo.py
scripts/scanpath.py
scripts/shtools_demo.py
scripts/termwot_demo.py
thebops/__init__.py
thebops/anyos.py
thebops/base.py
thebops/colours.py
thebops/counters.py
thebops/enhopa.py
thebops/errors.py
thebops/i18n.py
thebops/iscales.py
thebops/likeix.py
thebops/misc1.py
thebops/modinfo.py
thebops/opo.py
thebops/optparse.py
thebops/plustr1.py
thebops/plustr2.py
thebops/rexxbi.py
thebops/shtools.py
thebops/termwot.py
thebops.egg-info/PKG-INFO
thebops.egg-info/SOURCES.txt
thebops.egg-info/dependency_links.txt
thebops.egg-info/entry_points.txt
thebops.egg-info/namespace_packages.txt
thebops.egg-info/top_level.txt
thebops/tests/__init__.py
thebops/tests/tc_optik.py
thebops/tests/tc_optparsebase.py
thebops/tests/tc_rexxbi_x2x.py
thebops/tests/tc_rexxbiwords.py
thebops/tools/__init__.py
thebops/tools/asciibox.py
thebops/tools/callpy.py
thebops/tools/colours_demo.py
thebops/tools/counters_demo.py
thebops/tools/iscales_demo.py
thebops/tools/likeix_demo.py
thebops/tools/opo_demo.py
thebops/tools/optparse_demo.py
thebops/tools/rexxbi_demo.py
thebops/tools/shtools_demo.py
thebops/tools/sort_po.py
thebops/tools/termwot_demo.py
thebops/tools/xfind.py