Metadata-Version: 1.0
Name: thebops
Version: 0.1.16
Summary: Tobias Herp's bag of Python stuff
Home-page: UNKNOWN
Author: Tobias Herp
Author-email: tobias.herp@gmx.net
License: GPL
Platform: UNKNOWN
